MANIFEST.in
__info__.py
setup.py
./appomatic.egg-info/SOURCES.txt
./appomatic.egg-info/dependency_links.txt
./appomatic.egg-info/requires.txt
./appomatic.egg-info/top_level.txt
appomatic.egg-info/PKG-INFO
appomatic.egg-info/SOURCES.txt
appomatic.egg-info/dependency_links.txt
appomatic.egg-info/requires.txt
appomatic.egg-info/top_level.txt